hathor/__about__.py
hathor/__init__.py
hathor/__main__.py
hathor/hacks.py
hathor/project/__init__.py
hathor/project/builders/__init__.py
hathor/project/builders/copy.py
hathor/project/builders/modular.py
hathor/project/information/__init__.py
hathor/project/information/project.py
hathor/project/information/requirement_explorer.py
hathor/project/information/roblox_api_dump.py
hathor/project/information/source_file.py
hathor/project/information/source_ptns.py
hathor/project/information/source_root.py
hathor/project/source_processors/__init__.py
hathor/project/source_processors/instance_yaml_processor.py
hathor/project/source_processors/lua_processor.py
hathor/project/source_processors/lua_value_encoders.py
hathor/project/source_processors/processors.py
hathor/project/source_processors/source_processor.py
hathor/resources/__init__.py
hathor/resources/editorconfig_template.ini
hathor/resources/gitignore_base.txt
hathor/resources/hathor.project.schema.json
hathor/resources/hathor_loader.lua
hathor/resources/hathor_run.lua
hathor/resources/hathor_stub.lua
hathor/serve/__init__.py
hathor/serve/app.py
hathor/serve/change_tracker.py
hathor/serve/client.py
hathor/serve/models.py
hathor/serve/project_builder.py
hathor/serve/watch_files.py
hathor-0.0.30.dev0.dist-info/LICENSE.md
hathor-0.0.30.dev0.dist-info/METADATA
hathor-0.0.30.dev0.dist-info/WHEEL
hathor-0.0.30.dev0.dist-info/entry_points.txt
hathor-0.0.30.dev0.dist-info/top_level.txt
hathor-0.0.30.dev0.dist-info/RECORD
