Metadata-Version: 2.1
Name: hathor
Version: 0.0.30.dev0
Summary: A lua script combobulator aimed at roblox
Home-page: https://gitlab.com/rockit-tools/hathor
Author: BrinkerVII
Author-email: brinkervii@gmail.com
License: GPL-3
Keywords: roblox,studio,lua,build-tool,build,tool
Platform: UNKNOWN
Classifier: Development Status :: 4 - Beta
Classifier: Programming Language :: Python :: 3.8
Requires-Python: >=3.8
License-File: LICENSE.md
Requires-Dist: cachetools
Requires-Dist: click
Requires-Dist: click-spinner
Requires-Dist: flask
Requires-Dist: flask-restx
Requires-Dist: fs
Requires-Dist: pyyaml
Requires-Dist: requests
Requires-Dist: setuptools
Requires-Dist: watchdog
Requires-Dist: wheel
Requires-Dist: whichcraft
